watercrawl_openai/__init__.py
watercrawl_openai/plugins.py
watercrawl_openai/settings.py
watercrawl_openai-0.1.1.dist-info/LICENSE
watercrawl_openai-0.1.1.dist-info/METADATA
watercrawl_openai-0.1.1.dist-info/WHEEL
watercrawl_openai-0.1.1.dist-info/RECORD
