Metadata-Version: 2.3
Name: watercrawl-openai
Version: 0.1.1
Summary: WaterCrawl OpenAI Plugin
Author: AmirMohsen Asaran
Author-email: info@watercrawl.ai
Requires-Python: >=3.11
Classifier: Programming Language :: Python :: 3
Classifier: License :: OSI Approved :: MIT License
Classifier: Operating System :: OS Independent
Requires-Dist: openai (>=1.101.0,<2.0.0)
Requires-Dist: watercrawl-plugin (>=0.1.0)
Project-URL: Homepage, https://github.com/watercrawl/watercrawl-openai
Project-URL: Issues, https://github.com/watercrawl/watercrawl-openai/issues
